[
  {
    "domain": "jacksonsofkingfisher.com",
    "title": "Chevrolet Buick GMC Dealership Near Oklahoma City",
    "business_name": "",
    "country": "USA",
    "seo_score": 77,
    "tech_spend": 229335,
    "crawled_at": "2026-02-03T15:58:48.882087664Z",
    "technologies": [
      "Adobe Analytics",
      "Adobe Marketing Cloud",
      "Akamai Global Host",
      "Amazon",
      "Amazon WAF Blocked",
      "Apture Linking Platform",
      "Better Lead Generation Services",
      "Call to Visit",
      "Coming Soon Page",
      "Content Delivery Network",
      "DAV",
      "Dealer.com",
      "Financial Services Guide",
      "GZIP Module",
      "GetResponse",
      "GitHub Hosting",
      "Google Analytics",
      "Google My Business",
      "Google Related Website Sites",
      "Google Tag Manager",
      "LaunchDarkly",
      "New Relic",
      "Nginx",
      "PWA",
      "QUIC",
      "Site.pro",
      "SiteW",
      "Subversion",
      "Tailwind CSS",
      "Twitter Ads",
      "UTF-8",
      "Underscores",
      "VinSolutions",
      "YouTube",
      "dc.js",
      "shadcn ui"
    ]
  },
  {
    "domain": "wagnermotors.support",
    "title": "Wagner Motors | IT Support",
    "business_name": "",
    "country": "",
    "seo_score": 60,
    "tech_spend": 23837,
    "crawled_at": "2026-02-02T12:49:48.866590959Z",
    "technologies": [
      "Alternate Protocol",
      "BatCache",
      "Content Delivery Network",
      "Dealer.com",
      "Divi",
      "Elegant Themes",
      "EmbedPress",
      "Fastly",
      "Google Cloud DNS",
      "Google Font API",
      "Microsoft 365",
      "Microsoft Teams",
      "Nginx",
      "PHP",
      "Paycor",
      "Theme In WP",
      "Timely",
      "Trello",
      "UTF-8",
      "VinSolutions",
      "WordPress",
      "WordPress Multisite",
      "jQuery",
      "jsDelivr",
      "vAuto"
    ]
  },
  {
    "domain": "usecontactter.com",
    "title": "Contactter.ai | Complete AI Platform for Automotive Dealerships",
    "business_name": "",
    "country": "USA",
    "seo_score": 72,
    "tech_spend": 22872,
    "crawled_at": "2026-01-31T23:46:48.882425747Z",
    "technologies": [
      "Calendly",
      "Content Delivery Network",
      "Google",
      "Google Cloud DNS",
      "Google Font API",
      "Next.js",
      "Pleroma",
      "UTF-8",
      "Vercel",
      "VinSolutions",
      "YouTube"
    ]
  },
  {
    "domain": "trychckrd.info",
    "title": "Checkered AI - Facebook Marketplace Automation for Car Dealerships",
    "business_name": "",
    "country": "",
    "seo_score": 62,
    "tech_spend": 30408,
    "crawled_at": "2026-01-30T17:28:48.882758853Z",
    "technologies": [
      "Alternate Protocol",
      "Avochato",
      "Better Lead Generation Services",
      "Framer Sites",
      "Free Call",
      "Google",
      "Google Analytics",
      "Google Cloud CDN",
      "Google Tag Manager",
      "Ntent",
      "QUIC",
      "VinSolutions",
      "Yandex Hosting",
      "Zeald"
    ]
  },
  {
    "domain": "shrevinsolutions.com",
    "title": "ShreVin Solutions – Turning Tech Into Advantage",
    "business_name": "",
    "country": "IND",
    "seo_score": 70,
    "tech_spend": 21894,
    "crawled_at": "2026-01-23T16:58:43.440534108Z",
    "technologies": [
      "Alternate Protocol",
      "Apture Linking Platform",
      "Content Delivery Network",
      "Elementor",
      "EmbedPress",
      "Google Analytics",
      "Google Cloud DNS",
      "Google Font API",
      "Google Tag Manager",
      "LiteSpeed",
      "Metform Elemento",
      "NFOrce Internet",
      "PHP",
      "QUIC",
      "Theme In WP",
      "UTF-8",
      "VinSolutions",
      "WordPress",
      "WordPress Multisite",
      "jQuery"
    ]
  },
  {
    "domain": "mailerfree.com",
    "title": "MailerFree - Email Marketing Company",
    "business_name": "",
    "country": "IND",
    "seo_score": 60,
    "tech_spend": 8099,
    "crawled_at": "2026-01-23T16:45:24.310040624Z",
    "technologies": [
      "Better Lead Generation Services",
      "DAV",
      "Font Awesome",
      "LiteSpeed",
      "QUIC",
      "Tailwind CSS",
      "UTF-8",
      "VinSolutions"
    ]
  },
  {
    "domain": "jonferry.com",
    "title": "Jon Ferry",
    "business_name": "",
    "country": "JPN",
    "seo_score": 67,
    "tech_spend": 111860,
    "crawled_at": "2026-01-23T10:16:43.462985267Z",
    "technologies": [
      "AWS WAF Challenge",
      "Amazon CloudFront",
      "CloudFront",
      "Content Delivery Network",
      "Dealer.com",
      "Google Analytics",
      "Google Tag Manager",
      "Heroku",
      "Instagram Follow Button",
      "M247",
      "Next.js",
      "Pleroma",
      "SMC",
      "SiteW",
      "Tailwind CSS",
      "Twitter Ads",
      "UTF-8",
      "Vector Internet Services",
      "Vercel",
      "VinSolutions",
      "eLand",
      "shadcn ui"
    ]
  },
  {
    "domain": "hyundaiofakron.com",
    "title": "Hyundai Dealership in Cuyahoga Falls, OH",
    "business_name": "",
    "country": "BOL",
    "seo_score": 77,
    "tech_spend": 104935,
    "crawled_at": "2026-01-20T02:36:58.172662242Z",
    "technologies": [
      "AI Log",
      "Akamai Global Host",
      "Alternate Protocol",
      "Amazon WAF Blocked",
      "Apture Linking Platform",
      "Call to Visit",
      "Coming Soon Page",
      "ComplyAuto",
      "Content Delivery Network",
      "DAV",
      "Dealer.com",
      "Express",
      "Facebook Conversion Tracking",
      "Facebook Login",
      "Facebook Messenger Platform",
      "Facebook Pixel",
      "Facebook Reseller",
      "Facebook Tag API",
      "Financial Services Guide",
      "GZIP Module",
      "GetResponse",
      "GitHub Hosting",
      "Google Analytics",
      "Google Maps",
      "Google My Business",
      "Google Related Website Sites",
      "Google Tag Manager",
      "LaunchDarkly",
      "New Relic",
      "Nginx",
      "PWA",
      "QUIC",
      "Site.pro",
      "SiteW",
      "Subversion",
      "Tailwind CSS",
      "Tealium",
      "UTF-8",
      "Underscores",
      "University or College",
      "VinSolutions",
      "dc.js",
      "eLand",
      "shadcn ui"
    ]
  },
  {
    "domain": "autosctconsulting.com",
    "title": "Auto SCT Consulting & Training | Automotive Dealership Service consulting Training | 6015 Glenfinnan Ct, Dublin, Ohio 43017, USA",
    "business_name": "Auto Sct Consulting",
    "country": "USA",
    "seo_score": 77,
    "tech_spend": 168901,
    "crawled_at": "2026-01-18T18:52:43.428197367Z",
    "technologies": [
      "AWS WAF Challenge",
      "Alternate Protocol",
      "Amazon WAF Blocked",
      "Apture Linking Platform",
      "Content Delivery Network",
      "DAV",
      "Dealer.com",
      "Express",
      "Fastly",
      "Fastly CDN",
      "GZIP Module",
      "Google Analytics",
      "Google Related Website Sites",
      "Google Tag Manager",
      "Instagram Follow Button",
      "K2F",
      "KVH",
      "Microdata for Google Shopping",
      "NFOrce Internet",
      "PWA",
      "Perl",
      "QUIC",
      "SMC",
      "SiteW",
      "Subversion",
      "Thank You",
      "UTF-8",
      "Vector Internet Services",
      "VinSolutions",
      "WP Booking Calendar",
      "Wix",
      "Wix Media",
      "mlcom"
    ]
  },
  {
    "domain": "jeffwylerfortthomas.net",
    "title": "Jeff Wyler CDJR of Fort Thomas: Jeep, Chrysler, Dodge, RAM Dealership in Ft. Thomas, KY",
    "business_name": "",
    "country": "USA",
    "seo_score": 87,
    "tech_spend": 129935,
    "crawled_at": "2026-01-16T23:56:52.665887095Z",
    "technologies": [
      "Adobe Marketing Cloud",
      "Akamai Global Host",
      "Alternate Protocol",
      "Amazon WAF Blocked",
      "Apture Linking Platform",
      "Better Lead Generation Services",
      "Call to Visit",
      "Coming Soon Page",
      "ComplyAuto",
      "Content Delivery Network",
      "Dealer.com",
      "Edmunds",
      "Facebook Conversion Tracking",
      "Facebook Login",
      "Facebook Messenger Platform",
      "Facebook Pixel",
      "Facebook Reseller",
      "Facebook Tag API",
      "GZIP Module",
      "GetResponse",
      "GitHub Hosting",
      "Google Analytics",
      "Google My Business",
      "Google Related Website Sites",
      "Google Tag Manager",
      "LaunchDarkly",
      "Mopar",
      "New Relic",
      "Nginx",
      "PWA",
      "QUIC",
      "Site.pro",
      "SiteW",
      "Subversion",
      "Tailwind CSS",
      "UTF-8",
      "Underscores",
      "VinSolutions",
      "dc.js"
    ]
  },
  {
    "domain": "jamcmci.com",
    "title": "James McIntyre - Portfolio",
    "business_name": "",
    "country": "",
    "seo_score": 40,
    "tech_spend": 8000,
    "crawled_at": "2026-01-12T10:01:41.512859076Z",
    "technologies": [
      "Apache",
      "GZIP Module",
      "VinSolutions"
    ]
  },
  {
    "domain": "loupdb.com",
    "title": "Netsapiens CRM Integration | Loup",
    "business_name": "",
    "country": "",
    "seo_score": 57,
    "tech_spend": 99757,
    "crawled_at": "2025-12-31T09:19:38.322268303Z",
    "technologies": [
      "AWS WAF Challenge",
      "AgencyBloc",
      "Alternate Protocol",
      "Amazon WAF Blocked",
      "Apollo IO",
      "Apture Linking Platform",
      "Calendly",
      "Call to Visit",
      "Content Delivery Network",
      "DAV",
      "EZLynx",
      "Express",
      "Fastly",
      "Fastly CDN",
      "Financial Services Guide",
      "Freshdesk Support",
      "Freshworks CRM",
      "GZIP Module",
      "Google My Business",
      "Google Related Website Sites",
      "Google Workspace",
      "K2F",
      "Kayako",
      "Microdata for Google Shopping",
      "Microsoft Teams",
      "NFOrce Internet",
      "PWA",
      "Perl",
      "Propertyware",
      "QUIC",
      "RM Education",
      "Red Spot Interactive",
      "Redtail Technology",
      "SMC",
      "Salesforce",
      "Salesforce Experience Cloud",
      "Salesforce Hosted",
      "SiteW",
      "Sitelinks Search Box",
      "Subversion",
      "Trello",
      "UTF-8",
      "VTiger",
      "Vector Internet Services",
      "VinSolutions",
      "WP Booking Calendar",
      "Wix",
      "Wix Media",
      "YouTube",
      "Zendesk Embeddables",
      "ePages",
      "mlcom"
    ]
  },
  {
    "domain": "brainboxcrm.com",
    "title": "Brainbox Ai CRM",
    "business_name": "",
    "country": "GBR",
    "seo_score": 72,
    "tech_spend": 199070,
    "crawled_at": "2025-12-28T20:37:38.335751444Z",
    "technologies": [
      "Apture Linking Platform",
      "Authorize.net",
      "Better Lead Generation Services",
      "Cloudflare",
      "Cloudflare Web Analytics",
      "Content Delivery Network",
      "Fireblade",
      "Google",
      "Google Cloud CDN",
      "Google Cloud DNS",
      "Google Cloud Storage",
      "Google Font API",
      "No-Q",
      "Nuxt.js",
      "Oracle Cloud",
      "QUIC",
      "RM Education",
      "Salesforce Hosted",
      "UTF-8",
      "University or College",
      "VinSolutions",
      "YouTube",
      "shadcn ui"
    ]
  },
  {
    "domain": "activengage.com",
    "title": "ActivEngage Automotive Live Chat | Car Dealer Live Chat",
    "business_name": "ActivEngage",
    "country": "BEL",
    "seo_score": 77,
    "tech_spend": 124511,
    "crawled_at": "2025-12-28T15:32:03.319715643Z",
    "technologies": [
      "AWS WAF Challenge",
      "Alternate Protocol",
      "Amazon WAF Blocked",
      "Apture Linking Platform",
      "Bunny Fonts",
      "Cloudflare",
      "Content Delivery Network",
      "Cornerstone",
      "DAV",
      "EmbedPress",
      "Engage",
      "Essential Grid",
      "Facebook Conversion Tracking",
      "Facebook Login",
      "Facebook Messenger Platform",
      "Facebook Pixel",
      "Facebook Reseller",
      "Facebook Tag API",
      "Fontello",
      "Google",
      "Google Analytics",
      "Google Cloud DNS",
      "Google Font API",
      "Google Tag Manager",
      "HubSpot Conversations",
      "Hubspot",
      "Instagram Follow Button",
      "Lazy Load for WordPress",
      "LinkedIn Insights",
      "LinkedIn Pixel",
      "Microdata for Google Shopping",
      "Ninja Forms",
      "PHP",
      "Popup Maker for Wordpress",
      "Slider Revolution",
      "Twitter Ads",
      "UTF-8",
      "Vimeo",
      "VinSolutions",
      "WP Engine",
      "WhatsApp Sharing",
      "Woo Themes",
      "WordPress",
      "WordPress Multisite",
      "WordPress PopUp",
      "YouTube",
      "eLand",
      "iGoDigital"
    ]
  },
  {
    "domain": "foxfordusa.com",
    "title": "Fox Ford Grand Rapids, MI | New Ford & Used Car Dealership",
    "business_name": "",
    "country": "USA",
    "seo_score": 82,
    "tech_spend": 59765,
    "crawled_at": "2025-12-26T10:06:31.619025973Z",
    "technologies": [
      "Akamai Global Host",
      "Alternate Protocol",
      "Amazon WAF Blocked",
      "Apture Linking Platform",
      "Call to Visit",
      "Coming Soon Page",
      "Content Delivery Network",
      "Dealer.com",
      "ETranslate",
      "Express",
      "Fireblade",
      "FordDirect",
      "GZIP Module",
      "GetResponse",
      "GitHub Hosting",
      "Google Analytics",
      "Google Maps",
      "Google My Business",
      "Google Related Website Sites",
      "Google Tag Manager",
      "Instagram Follow Button",
      "LaunchDarkly",
      "New Relic",
      "Nginx",
      "No-Q",
      "PWA",
      "QUIC",
      "Site.pro",
      "SiteW",
      "Tailwind CSS",
      "UTF-8",
      "Underscores",
      "VinSolutions",
      "YouTube",
      "dc.js",
      "shadcn ui"
    ]
  },
  {
    "domain": "paa.org",
    "title": "PAA - Pennsylvania Automotive Association",
    "business_name": "",
    "country": "",
    "seo_score": 62,
    "tech_spend": 140477,
    "crawled_at": "2025-12-26T07:40:38.36521118Z",
    "technologies": [
      "AWS WAF Challenge",
      "Amazon WAF Blocked",
      "Apture Linking Platform",
      "Aruba",
      "ComplyAuto",
      "Content Delivery Network",
      "DAV",
      "Express",
      "Fastly",
      "Fastly CDN",
      "Fireblade",
      "FormSubmit",
      "GZIP Module",
      "GitHub Hosting",
      "Microdata for Google Shopping",
      "NFOrce Internet",
      "PWA",
      "Perl",
      "Pico CSS",
      "QUIC",
      "SMC",
      "SiteW",
      "Subversion",
      "Tailwind CSS",
      "UTF-8",
      "Vector Internet Services",
      "VinSolutions",
      "WP Booking Calendar",
      "Wix",
      "Wix Media",
      "eLand",
      "mlcom"
    ]
  },
  {
    "domain": "ourismanhyundai.com",
    "title": "Hyundai Dealership Laurel MD| Columbia | Baltimore",
    "business_name": "",
    "country": "USA",
    "seo_score": 82,
    "tech_spend": 98403,
    "crawled_at": "2025-12-25T21:29:15.736702185Z",
    "technologies": [
      "AI Log",
      "Akamai Global Host",
      "Alternate Protocol",
      "Apture Linking Platform",
      "Call to Visit",
      "Coming Soon Page",
      "Content Delivery Network",
      "Dealer.com",
      "Express",
      "Facebook Conversion Tracking",
      "Facebook Login",
      "Facebook Messenger Platform",
      "Facebook Pixel",
      "Facebook Reseller",
      "Facebook Tag API",
      "Financial Services Guide",
      "GZIP Module",
      "Google Analytics",
      "Google Maps",
      "Google My Business",
      "Google Related Website Sites",
      "Google Tag Manager",
      "LaunchDarkly",
      "Nginx",
      "PWA",
      "QUIC",
      "Site.pro",
      "SiteW",
      "Tailwind CSS",
      "Tealium",
      "UTF-8",
      "Underscores",
      "University or College",
      "VinSolutions",
      "YouTube",
      "dc.js",
      "shadcn ui"
    ]
  },
  {
    "domain": "gopopl.com",
    "title": "Popl | The In-Person Go-To-Market Platform For Events & Conferences",
    "business_name": "",
    "country": "",
    "seo_score": 67,
    "tech_spend": 217656,
    "crawled_at": "2025-12-25T11:31:38.352735881Z",
    "technologies": [
      "Amazon WAF Blocked",
      "Apollo IO",
      "App Store",
      "Apture Linking Platform",
      "Better Lead Generation Services",
      "Cloudflare",
      "Cloudflare CDN",
      "Fireblade",
      "Font Awesome",
      "FormSubmit",
      "GZIP Module",
      "Google",
      "Google Cloud DNS",
      "Google Font API",
      "Google My Business",
      "Google Related Website Sites",
      "Heroku",
      "HubSpot Conversations",
      "Hubspot",
      "Instagram Follow Button",
      "Intercom",
      "License Buttons",
      "LottieFiles",
      "Microdata for Google Shopping",
      "Perl",
      "QUIC",
      "Salesforce Hosted",
      "Shopify",
      "Shopify Collabs",
      "Shopify Payments",
      "Smart App Banner",
      "Tailwind CSS",
      "Twitter Ads",
      "UTF-8",
      "Vector Internet Services",
      "VinSolutions",
      "WordPress SEO Structured Data Schema Plugin",
      "YouTube",
      "hCaptcha",
      "monday.com",
      "reCAPTCHA",
      "shadcn ui"
    ]
  },
  {
    "domain": "amherstsubaru.com",
    "title": "New and Used Subaru Dealer in Amherst, NH | Amherst Subaru",
    "business_name": "",
    "country": "",
    "seo_score": 72,
    "tech_spend": 29935,
    "crawled_at": "2025-12-25T08:35:37.350861785Z",
    "technologies": [
      "Akamai Global Host",
      "Alternate Protocol",
      "Amazon WAF Blocked",
      "Apture Linking Platform",
      "Call to Visit",
      "Coming Soon Page",
      "ComplyAuto",
      "Content Delivery Network",
      "DAV",
      "Dealer.com",
      "Express",
      "Facebook Conversion Tracking",
      "Facebook Login",
      "Facebook Messenger Platform",
      "Facebook Pixel",
      "Facebook Reseller",
      "Facebook Tag API",
      "GZIP Module",
      "GetResponse",
      "GitHub Hosting",
      "Google Analytics",
      "Google Customer Reviews",
      "Google My Business",
      "Google Related Website Sites",
      "Google Tag Manager",
      "LaunchDarkly",
      "New Relic",
      "Nginx",
      "PWA",
      "Parcel",
      "QUIC",
      "Site.pro",
      "SiteW",
      "Tailwind CSS",
      "Twitter Ads",
      "UTF-8",
      "Underscores",
      "VinSolutions",
      "dc.js"
    ]
  },
  {
    "domain": "dontbetrippin.com",
    "title": "New & Used Hyundai Dealer in Olive Branch, MS | Homer Skelton Hyundai",
    "business_name": "",
    "country": "BOL",
    "seo_score": 77,
    "tech_spend": 101935,
    "crawled_at": "2025-12-23T16:49:07.329405415Z",
    "technologies": [
      "AI Log",
      "Akamai Global Host",
      "Alternate Protocol",
      "Amazon WAF Blocked",
      "Apture Linking Platform",
      "Call to Visit",
      "Coming Soon Page",
      "Content Delivery Network",
      "Dealer.com",
      "DoubleClick Bid Manager",
      "Express",
      "Financial Services Guide",
      "GZIP Module",
      "GetResponse",
      "GitHub Hosting",
      "Google Analytics",
      "Google Maps",
      "Google My Business",
      "Google Related Website Sites",
      "Google Tag Manager",
      "LaunchDarkly",
      "New Relic",
      "Nginx",
      "PWA",
      "QUIC",
      "Site.pro",
      "SiteW",
      "Tailwind CSS",
      "Tealium",
      "Twitter Ads",
      "UTF-8",
      "Underscores",
      "University or College",
      "VinSolutions",
      "dc.js",
      "shadcn ui"
    ]
  },
  {
    "domain": "level10racing.com",
    "title": "Home - Level 10 Racing",
    "business_name": "",
    "country": "",
    "seo_score": 55,
    "tech_spend": 8998,
    "crawled_at": "2025-12-19T09:34:32.752685684Z",
    "technologies": [
      "Alternate Protocol",
      "Apture Linking Platform",
      "Divi",
      "Elegant Themes",
      "EmbedPress",
      "Endurance Page Cache",
      "Fastly",
      "GZIP Module",
      "Google Cloud DNS",
      "Google Font API",
      "Google My Business",
      "Instagram Follow Button",
      "Jetpack",
      "Meta Slider for WordPress",
      "Microdata for Google Shopping",
      "Nginx",
      "PHP",
      "Team Members",
      "Theme In WP",
      "UTF-8",
      "VinSolutions",
      "WPForms",
      "WoWonder",
      "Woo Themes",
      "WordPress",
      "WordPress Multisite",
      "WordPress Stats",
      "jQuery"
    ]
  },
  {
    "domain": "9cloudsinc.com",
    "title": "9 Clouds: Digital Lead Generation Agency",
    "business_name": "9 Clouds",
    "country": "USA",
    "seo_score": 77,
    "tech_spend": 42147,
    "crawled_at": "2025-12-14T14:40:56.041191728Z",
    "technologies": [
      "Alternate Protocol",
      "Better Lead Generation Services",
      "Content Delivery Network",
      "CoreUI",
      "EmbedPress",
      "Google Analytics",
      "Google Cloud DNS",
      "Google Font API",
      "Google My Business",
      "Google Related Website Sites",
      "Google Tag Manager",
      "HubSpot Conversations",
      "HubSpot WordPress Plugin",
      "Hubspot",
      "Instagram Follow Button",
      "Microdata for Google Shopping",
      "Nginx",
      "PHP",
      "Stackable Page Builder Gutenberg Blocks",
      "Thank You",
      "Theme In WP",
      "Twitter Ads",
      "UTF-8",
      "VinSolutions",
      "WP Engine",
      "WordPress",
      "WordPress Multisite",
      "YouTube",
      "jQuery"
    ]
  },
  {
    "domain": "allendigital.studio",
    "title": "Allen Digital Studio | Creative Digital Solutions",
    "business_name": "",
    "country": "USA",
    "seo_score": 77,
    "tech_spend": 198335,
    "crawled_at": "2025-12-13T18:37:56.026966569Z",
    "technologies": [
      "AWS WAF Challenge",
      "Alternate Protocol",
      "Apture Linking Platform",
      "Better Lead Generation Services",
      "Coming Soon Page",
      "Content Delivery Network",
      "DealerCenter",
      "ImageKit.io",
      "Microdata for Google Shopping",
      "Netlify",
      "Next.js",
      "Pleroma",
      "Tailwind CSS",
      "Telegram",
      "UTF-8",
      "Vector Internet Services",
      "Vercel",
      "VinSolutions",
      "commercetools",
      "shadcn ui"
    ]
  },
  {
    "domain": "mindfultech.services",
    "title": "Mindful Tech | Build the Minds That Work for You",
    "business_name": "",
    "country": "USA",
    "seo_score": 77,
    "tech_spend": 35574,
    "crawled_at": "2025-12-13T09:46:56.042588613Z",
    "technologies": [
      "Apture Linking Platform",
      "Calendly",
      "Content Delivery Network",
      "DriveCentric",
      "Instagram Follow Button",
      "Jetpack",
      "Netlify",
      "Next.js",
      "Pleroma",
      "QUIC",
      "Tailwind CSS",
      "Twitter Ads",
      "UTF-8",
      "VinSolutions"
    ]
  },
  {
    "domain": "purplauto.ai",
    "title": "Purplauto AI",
    "business_name": "purplauto.ai",
    "country": "",
    "seo_score": 62,
    "tech_spend": 21378,
    "crawled_at": "2025-12-10T17:24:57.33239614Z",
    "technologies": [
      "Alternate Protocol",
      "Animate It",
      "Apture Linking Platform",
      "Content Delivery Network",
      "EmbedPress",
      "Google Analytics",
      "Google Cloud DNS",
      "Google Font API",
      "Google Related Website Sites",
      "Google Tag Manager",
      "IcoMoon",
      "LiteSpeed",
      "Microdata for Google Shopping",
      "Nectar Slide Plugin",
      "PHP",
      "QUIC",
      "Salient",
      "Theme In WP",
      "UTF-8",
      "VinSolutions",
      "WPBakery",
      "WordPress",
      "WordPress Multisite",
      "jQuery"
    ]
  },
  {
    "domain": "tekion.com",
    "title": "Tekion | First End-to-End Cloud Native Automotive Platform",
    "business_name": "",
    "country": "",
    "seo_score": 62,
    "tech_spend": 106599,
    "crawled_at": "2025-12-09T09:17:25.036284103Z",
    "technologies": [
      "AWS WAF Challenge",
      "Amazon CloudFront",
      "Apture Linking Platform",
      "Cisco/Arrowpoint Content Service Switch",
      "CloudFront",
      "Cornerstone",
      "Fireblade",
      "GZIP Module",
      "Google Cloud DNS",
      "Google Font API",
      "Instagram Follow Button",
      "NFOrce Internet",
      "Next.js",
      "Pleroma",
      "Tekion",
      "Twitter Ads",
      "UTF-8",
      "Underscores",
      "VinSolutions"
    ]
  },
  {
    "domain": "vendoraccountability.com",
    "title": "Automotive Dealer Vendor Accountability – VendorAccountability.com",
    "business_name": "",
    "country": "",
    "seo_score": 60,
    "tech_spend": 8351,
    "crawled_at": "2025-12-07T09:05:56.331022528Z",
    "technologies": [
      "Alternate Protocol",
      "Coming Soon Page",
      "Content Delivery Network",
      "EmbedPress",
      "Google Cloud DNS",
      "Google Font API",
      "Gutenberg Blocks by Kadence Blocks",
      "Instagram Follow Button",
      "Jetpack",
      "Kadence WP",
      "LearnDash",
      "LiteSpeed",
      "PHP",
      "QUIC",
      "Theme In WP",
      "UTF-8",
      "VinSolutions",
      "Woo Themes",
      "WooCommerce",
      "WooCommerce Checkout",
      "WordPress",
      "WordPress Multisite",
      "WordPress Stats",
      "jQuery"
    ]
  },
  {
    "domain": "dealergo.ai",
    "title": "DealerGo",
    "business_name": "",
    "country": "",
    "seo_score": 57,
    "tech_spend": 19066,
    "crawled_at": "2025-12-01T22:00:46.367367656Z",
    "technologies": [
      "Amazon",
      "Amazon CloudFront",
      "Amazon Route 53",
      "Amazon S3 CDN",
      "CloudFront",
      "Content Delivery Network",
      "DriveCentric",
      "GZIP Module",
      "Next.js",
      "Pleroma",
      "Salesforce Hosted",
      "Tailwind CSS",
      "VinSolutions",
      "shadcn ui"
    ]
  },
  {
    "domain": "alexcastro.co",
    "title": "Alex Castro - AI Enthusiast & Web Developer",
    "business_name": "",
    "country": "USA",
    "seo_score": 77,
    "tech_spend": 189938,
    "crawled_at": "2025-11-21T04:03:19.453967853Z",
    "technologies": [
      "AWS WAF Challenge",
      "Better Lead Generation Services",
      "CDN JS",
      "Cloudflare",
      "Cloudflare CDN",
      "Coming Soon Page",
      "Content Delivery Network",
      "Cornerstone",
      "Fastly",
      "GZIP Module",
      "GitHub Hosting",
      "Google",
      "Google Cloud DNS",
      "Google Font API",
      "Google My Business",
      "Python",
      "QUIC",
      "Salesforce Hosted",
      "UTF-8",
      "VinSolutions",
      "jsDelivr"
    ]
  },
  {
    "domain": "quantumconsultingsolutions.io",
    "title": "Home Page",
    "business_name": "",
    "country": "",
    "seo_score": 55,
    "tech_spend": 15963,
    "crawled_at": "2025-11-20T22:51:19.45125588Z",
    "technologies": [
      "Apture Linking Platform",
      "Authorize.net",
      "Cloudflare",
      "Cloudflare Web Analytics",
      "Content Delivery Network",
      "Fireblade",
      "Google",
      "Google Cloud CDN",
      "Google Cloud DNS",
      "Google Cloud Storage",
      "Google Font API",
      "Instagram Follow Button",
      "Nuxt.js",
      "QUIC",
      "Tailwind CSS",
      "UTF-8",
      "VinSolutions",
      "YouTube",
      "reCAPTCHA"
    ]
  },
  {
    "domain": "bestcrmsoftwareforcardealerships.com",
    "title": "In-Depth Analysis and Rankings of Best CRM Software for Car Dealerships",
    "business_name": "",
    "country": "",
    "seo_score": 67,
    "tech_spend": 92590,
    "crawled_at": "2025-11-20T11:36:19.436660411Z",
    "technologies": [
      "Amazon",
      "Amazon CloudFront",
      "Amazon Route 53",
      "Amazon S3 CDN",
      "Better Lead Generation Services",
      "Bulma",
      "CDK Global",
      "CloudFront",
      "Content Delivery Network",
      "Fireblade",
      "GZIP Module",
      "Google Analytics",
      "Google Tag Manager",
      "Hotjar",
      "Instagram Follow Button",
      "NFOrce Internet",
      "ProMax Unlimited",
      "RM Education",
      "Twitter Ads",
      "UTF-8",
      "VinSolutions"
    ]
  },
  {
    "domain": "jayknowsauto.com",
    "title": "JAY Knows Auto – Automotive Advertising",
    "business_name": "",
    "country": "",
    "seo_score": 55,
    "tech_spend": 23622,
    "crawled_at": "2025-11-18T02:17:04.992634535Z",
    "technologies": [
      "Alternate Protocol",
      "Apache",
      "Compact WP Audio Player",
      "Contact Form Plugin",
      "Dealer.com",
      "EmbedPress",
      "Google Analytics",
      "Google Cloud DNS",
      "Google Font API",
      "Google My Business",
      "Google Tag Manager",
      "Gravity",
      "Gravity Forms",
      "Ninetheme",
      "PHP",
      "SMC",
      "Subversion",
      "Theme In WP",
      "UTF-8",
      "VinSolutions",
      "WPBakery",
      "WordPress",
      "WordPress Multisite",
      "YouTube",
      "jQuery",
      "reCAPTCHA"
    ]
  },
  {
    "domain": "digitaldealershipsystem.com",
    "title": "Digital Dealership System - Dealership KPI Leaderboards",
    "business_name": "Digital Dealership System",
    "country": "USA",
    "seo_score": 82,
    "tech_spend": 107440,
    "crawled_at": "2025-11-17T11:41:05.049788357Z",
    "technologies": [
      "AdRoll",
      "Agoda",
      "Alternate Protocol",
      "CDK Global",
      "Content Delivery Network",
      "DC74",
      "Elementor",
      "EmbedPress",
      "Express",
      "Google Analytics",
      "Google Tag Manager",
      "Line2",
      "LinkedIn Insights",
      "LinkedIn Pixel",
      "LiteSpeed",
      "Microdata for Google Shopping",
      "NFOrce Internet",
      "PHP",
      "Perl",
      "QUIC",
      "QUIC.cloud",
      "Sitelinks Search Box",
      "Table Addons for Elementor",
      "Tekion",
      "UTF-8",
      "VinSolutions",
      "WordPress",
      "WordPress Multisite"
    ]
  },
  {
    "domain": "kelvinsolutionsllc.com",
    "title": "KELVIN Solutions, LLC - Light • Control • Simplified",
    "business_name": "",
    "country": "",
    "seo_score": 55,
    "tech_spend": 33601,
    "crawled_at": "2025-11-17T06:26:05.016222027Z",
    "technologies": [
      "Adobe Creative Cloud WebFonts",
      "Aruba",
      "Express",
      "FormSubmit",
      "GZIP Module",
      "Instagram Follow Button",
      "Line2",
      "Magento Enterprise",
      "Microdata for Google Shopping",
      "QUIC",
      "SiteW",
      "Squarespace",
      "UTF-8",
      "VinSolutions",
      "WordPress SEO Structured Data Schema Plugin",
      "eLand"
    ]
  },
  {
    "domain": "premiovin.com",
    "title": "Premiovin Solutions Nigeria Limited",
    "business_name": "",
    "country": "NGA",
    "seo_score": 70,
    "tech_spend": 20508,
    "crawled_at": "2025-11-15T11:44:04.999013274Z",
    "technologies": [
      "Apache",
      "CDN JS",
      "Cloudflare",
      "Cloudflare CDN",
      "GZIP Module",
      "Google Cloud DNS",
      "Google Font API",
      "IcoMoon",
      "Instagram Follow Button",
      "VinSolutions"
    ]
  },
  {
    "domain": "alvinitsolutions.in",
    "title": "Home-4 - Alvin IT Solutions",
    "business_name": "",
    "country": "IND",
    "seo_score": 82,
    "tech_spend": 23214,
    "crawled_at": "2025-11-15T00:44:04.998217973Z",
    "technologies": [
      "Alternate Protocol",
      "Click to Chat for WhatsApp",
      "Contact Form Plugin",
      "Content Delivery Network",
      "Elementor",
      "EmbedPress",
      "FreeCSSTemplates",
      "Google Analytics",
      "Google Cloud DNS",
      "Google Customer Reviews",
      "Google Font API",
      "Google Maps",
      "Google Related Website Sites",
      "Google Tag Manager",
      "Header, Footer and Blocks for Elementor",
      "Instagram Follow Button",
      "LiteSpeed",
      "Microdata for Google Shopping",
      "NFOrce Internet",
      "Ntent",
      "PHP",
      "Python",
      "QUIC",
      "Sitelinks Search Box",
      "Table Addons for Elementor",
      "Theme In WP",
      "TrustIndex",
      "UTF-8",
      "University or College",
      "VinSolutions",
      "WoWonder",
      "WordPress",
      "WordPress Multisite",
      "jQuery"
    ]
  },
  {
    "domain": "communify.io",
    "title": "Communify – intelligent engagement platform",
    "business_name": "",
    "country": "USA",
    "seo_score": 65,
    "tech_spend": 45507,
    "crawled_at": "2025-11-12T12:17:38.881632639Z",
    "technologies": [
      "Alternate Protocol",
      "Column Shortcodes",
      "Contento",
      "Cornerstone",
      "EmbedPress",
      "GZIP Module",
      "Google Cloud DNS",
      "Google Font API",
      "Instagram Follow Button",
      "Kriesi.at",
      "Nginx",
      "PHP",
      "Parallels Plesk Panel",
      "Theme In WP",
      "Twitter Ads",
      "UTF-8",
      "VinSolutions",
      "WordPress",
      "WordPress Multisite",
      "jQuery"
    ]
  },
  {
    "domain": "avinsolutions.com",
    "title": "Avin Solutions | Website Design Serivces",
    "business_name": "",
    "country": "",
    "seo_score": 55,
    "tech_spend": 8441,
    "crawled_at": "2025-11-11T21:14:38.887444641Z",
    "technologies": [
      "AWS WAF Challenge",
      "Alternate Protocol",
      "Apache",
      "DAV",
      "Divi",
      "Elegant Themes",
      "GZIP Module",
      "Google",
      "Google Cloud CDN",
      "Google Cloud DNS",
      "Google Font API",
      "PHP",
      "QUIC",
      "Theme In WP",
      "UTF-8",
      "VinSolutions",
      "Woo Themes",
      "WordPress",
      "WordPress Multisite",
      "jQuery"
    ]
  },
  {
    "domain": "arizonamuscle.com",
    "title": "Arizona Muscle - Porsche, Exotic and Specialty Car Sales",
    "business_name": "Arizona Muscle - Porsche, Exotic and Specialty Car Sales",
    "country": "",
    "seo_score": 60,
    "tech_spend": 8241,
    "crawled_at": "2025-11-09T22:37:01.597388317Z",
    "technologies": [
      "Alternate Protocol",
      "Apache",
      "Divi",
      "Elegant Themes",
      "GZIP Module",
      "Google",
      "Google Cloud CDN",
      "Google Cloud DNS",
      "Google Font API",
      "Microdata for Google Shopping",
      "PHP",
      "Theme In WP",
      "UTF-8",
      "VinSolutions",
      "WP Super Cache",
      "Woo Themes",
      "WordPress",
      "WordPress Multisite",
      "jQuery"
    ]
  },
  {
    "domain": "bhtowingcashforcar.com.au",
    "title": "BH Towing – Get Top Cash For Car Adelaide",
    "business_name": "",
    "country": "AUS",
    "seo_score": 75,
    "tech_spend": 22355,
    "crawled_at": "2025-11-09T16:31:54.111173319Z",
    "technologies": [
      "Alternate Protocol",
      "Better Lead Generation Services",
      "Contact Form Plugin",
      "Elementor",
      "EmbedPress",
      "Font Awesome",
      "Google Cloud DNS",
      "Google Font API",
      "IcoMoon",
      "Instagram Follow Button",
      "LiteSpeed",
      "NFOrce Internet",
      "PHP",
      "QUIC",
      "Tailwind CSS",
      "Theme In WP",
      "Twitter Ads",
      "UTF-8",
      "VinSolutions",
      "WordPress",
      "WordPress Multisite",
      "jQuery"
    ]
  },
  {
    "domain": "revitupcall.com",
    "title": "RevItUpCalls – Professional CRM Support and Remote Calling Services for Car Dealerships.",
    "business_name": "",
    "country": "",
    "seo_score": 77,
    "tech_spend": 42647,
    "crawled_at": "2025-11-08T22:21:35.994139079Z",
    "technologies": [
      "AWS WAF Challenge",
      "Alternate Protocol",
      "Automattic",
      "Better Lead Generation Services",
      "Content Delivery Network",
      "EmbedPress",
      "GDPR Consent Management Platform",
      "Jetpack",
      "Jetpack Site Accelerator",
      "Nginx",
      "Prospective",
      "Tailwind CSS",
      "UTF-8",
      "VinSolutions",
      "WordPress",
      "WordPress Multisite",
      "WordPress Stats"
    ]
  },
  {
    "domain": "bluvinsolutions.com",
    "title": "Bluvin Solutions",
    "business_name": "",
    "country": "",
    "seo_score": 45,
    "tech_spend": 8063,
    "crawled_at": "2025-11-05T10:25:16.597433955Z",
    "technologies": [
      "ElementUI",
      "Google",
      "Google Cloud DNS",
      "Google Font API",
      "LiteSpeed",
      "QUIC",
      "VinSolutions"
    ]
  },
  {
    "domain": "kelvinsolutions.net",
    "title": "Track Your Performance with Our Sports Tracker",
    "business_name": "",
    "country": "",
    "seo_score": 67,
    "tech_spend": 39032,
    "crawled_at": "2025-11-04T17:17:48.482681749Z",
    "technologies": [
      "Alternate Protocol",
      "GitHub Hosting",
      "GoDaddy",
      "Google",
      "Google Analytics",
      "Google Cloud DNS",
      "Google Font API",
      "Google My Business",
      "Google Related Website Sites",
      "Google Tag Manager",
      "Line2",
      "PWA",
      "UTF-8",
      "VinSolutions",
      "Wangsu",
      "Website Tonight",
      "YouTube"
    ]
  },
  {
    "domain": "entrepreneurshipmiami.com",
    "title": "Start a Business in 8 Weeks - Miami Entrepreneurship Institute",
    "business_name": "Miami Entrepreneurship Institute",
    "country": "GBR",
    "seo_score": 82,
    "tech_spend": 52155,
    "crawled_at": "2025-11-04T04:59:38.972918319Z",
    "technologies": [
      "AWS WAF Challenge",
      "Alternate Protocol",
      "Better Lead Generation Services",
      "Cloudflare",
      "Contact Form Plugin",
      "Content Delivery Network",
      "EmbedPress",
      "Facebook Conversion Tracking",
      "Facebook Login",
      "Facebook Messenger Platform",
      "Facebook Pixel",
      "Facebook Reseller",
      "Facebook Tag API",
      "GoDaddy",
      "Google Analytics",
      "Google Cloud DNS",
      "Google Font API",
      "Google My Business",
      "Google Tag Manager",
      "MailChimp",
      "Mesmerize Companion",
      "Microdata for Google Shopping",
      "PHP",
      "QUIC",
      "Tailwind CSS",
      "Theme In WP",
      "UTF-8",
      "University or College",
      "VinSolutions",
      "Wangsu",
      "WordPress",
      "WordPress Multisite",
      "jQuery",
      "reCAPTCHA"
    ]
  },
  {
    "domain": "vikvinsolutions.co.uk",
    "title": "VikVin Solutions",
    "business_name": "",
    "country": "GBR",
    "seo_score": 72,
    "tech_spend": 25024,
    "crawled_at": "2025-11-04T04:57:58.245966365Z",
    "technologies": [
      "Apture Linking Platform",
      "Authorize.net",
      "Content Delivery Network",
      "GZIP Module",
      "Google",
      "Google Cloud CDN",
      "Google Cloud DNS",
      "Google Cloud Storage",
      "Google Font API",
      "Nuxt.js",
      "Tailwind CSS",
      "UTF-8",
      "Unsplash",
      "VinSolutions",
      "reCAPTCHA"
    ]
  },
  {
    "domain": "georgiawineproducers.org",
    "title": "Georgia Wine Producers - Home",
    "business_name": "",
    "country": "",
    "seo_score": 50,
    "tech_spend": 47436,
    "crawled_at": "2025-11-04T02:02:39.006135871Z",
    "technologies": [
      "Amazon",
      "Amazon CloudFront",
      "Amazon Route 53",
      "CloudFront",
      "Cloudflare",
      "Cloudflare CDN",
      "Contento",
      "DoubleClick Bid Manager",
      "Ecwid Ecommerce Shopping Cart",
      "Facebook Reseller",
      "Font Awesome",
      "Forethought",
      "GZIP Module",
      "Google",
      "Google Analytics",
      "Google Cloud DNS",
      "Google Maps",
      "Google My Business",
      "Google Tag Manager",
      "Storyblocks",
      "Twitter Ads",
      "UTF-8",
      "University or College",
      "UserVoice",
      "VinSolutions",
      "Wild Apricot",
      "YouTube",
      "Zendesk Embeddables",
      "elevio"
    ]
  },
  {
    "domain": "michaeljaggers.net",
    "title": "W. Michael Jaggers | About",
    "business_name": "",
    "country": "",
    "seo_score": 67,
    "tech_spend": 41380,
    "crawled_at": "2025-11-03T20:51:35.80998667Z",
    "technologies": [
      "AWS WAF Challenge",
      "Dealer.com",
      "GitHub Hosting",
      "Google",
      "Google Cloud DNS",
      "Google Font API",
      "Microsoft Azure",
      "QUIC",
      "Tailwind CSS",
      "UTF-8",
      "VinSolutions",
      "Visual Studio"
    ]
  },
  {
    "domain": "debvin.com.ng",
    "title": "Debvin Web Solutions - Best Website Developer in Lagos",
    "business_name": "",
    "country": "NGA",
    "seo_score": 77,
    "tech_spend": 20816,
    "crawled_at": "2025-11-03T16:38:38.886694361Z",
    "technologies": [
      "Better Lead Generation Services",
      "Google Related Website Sites",
      "Instagram Follow Button",
      "QUIC",
      "Twitter Ads",
      "VinSolutions",
      "Web3Forms",
      "YouTube",
      "jsDelivr"
    ]
  },
  {
    "domain": "heymia.com",
    "title": "Hey Mia: Your 24/7 Automotive AI Phone Agent",
    "business_name": "",
    "country": "",
    "seo_score": 67,
    "tech_spend": 196636,
    "crawled_at": "2025-11-03T03:20:38.968942262Z",
    "technologies": [
      "AJAX Libraries API",
      "Amazon",
      "Amazon CloudFront",
      "Animate It",
      "Apture Linking Platform",
      "AutoSweet",
      "BunnyCDN",
      "BunnyCDN General",
      "CDK Global",
      "CloudFront",
      "Content Delivery Network",
      "Dealer-FX",
      "DealerInspire",
      "DriveCentric",
      "Express",
      "Facebook Conversion Tracking",
      "Facebook Login",
      "Facebook Messenger Platform",
      "Facebook Pixel",
      "Facebook Reseller",
      "Facebook Tag API",
      "GZIP Module",
      "Google",
      "Google Analytics",
      "Google Cloud DNS",
      "Google Font API",
      "Google My Business",
      "Google Related Website Sites",
      "Google Tag Manager",
      "LinkedIn Insights",
      "LinkedIn Pixel",
      "QUIC",
      "Tailwind CSS",
      "Tekion",
      "VinSolutions",
      "WF Cookie Consent",
      "Webflow",
      "reCAPTCHA",
      "vAuto"
    ]
  },
  {
    "domain": "fstream.io",
    "title": "Fstream | Consulting",
    "business_name": "Fstream",
    "country": "DEU",
    "seo_score": 72,
    "tech_spend": 474473,
    "crawled_at": "2025-11-02T22:20:38.981001757Z",
    "technologies": [
      "AWS WAF Challenge",
      "Alternate Protocol",
      "Amazon WAF Blocked",
      "Apache",
      "Apture Linking Platform",
      "Aruba",
      "Better Lead Generation Services",
      "Content Delivery Network",
      "Corporate Governance and Regulatory Compliance",
      "Creatio CRM",
      "DC74",
      "Endis",
      "Express",
      "Fastly",
      "Fastly CDN",
      "Financial Services Guide",
      "Fireblade",
      "FormSubmit",
      "GZIP Module",
      "GenerateBlocks",
      "GitHub Hosting",
      "Google Related Website Sites",
      "InitiativeS",
      "Instagram Follow Button",
      "M247",
      "Microdata for Google Shopping",
      "NFOrce Internet",
      "Oracle Cloud",
      "PWA",
      "Pico CSS",
      "Pipedrive",
      "QUIC",
      "SMC",
      "Salesforce",
      "Salesforce Experience Cloud",
      "Salesforce Hosted",
      "Seflow Italy",
      "SiteW",
      "Subversion",
      "Tailwind CSS",
      "UTF-8",
      "University or College",
      "Vector Internet Services",
      "VinSolutions",
      "Wix",
      "Wix Media",
      "eLand",
      "mlcom"
    ]
  },
  {
    "domain": "nithvinsolutions.com",
    "title": "Nithvin Solutions",
    "business_name": "",
    "country": "IND",
    "seo_score": 60,
    "tech_spend": 8719,
    "crawled_at": "2025-11-02T09:49:56.25474238Z",
    "technologies": [
      "Alternate Protocol",
      "Apture Linking Platform",
      "Bulma",
      "Contact Form Plugin",
      "EmbedPress",
      "Google Cloud DNS",
      "Google Font API",
      "IcoMoon",
      "LiteSpeed",
      "NFOrce Internet",
      "PHP",
      "QUIC",
      "Slider Revolution",
      "Tailwind CSS",
      "Theme In WP",
      "UTF-8",
      "VinSolutions",
      "WPBakery",
      "WordPress",
      "WordPress Multisite",
      "jQuery"
    ]
  },
  {
    "domain": "bdcangels.com",
    "title": "BDC Angels | Not All Angels Have Wings— Some of Us Wear Headsets!",
    "business_name": "",
    "country": "USA",
    "seo_score": 77,
    "tech_spend": 33668,
    "crawled_at": "2025-11-01T14:15:25.031725592Z",
    "technologies": [
      "Cloudflare",
      "Cloudflare CDN",
      "Content Delivery Network",
      "Fastly",
      "Hubspot Knowledge Base",
      "IcoMoon",
      "Instagram Follow Button",
      "Twitter Ads",
      "UTF-8",
      "VinSolutions",
      "YouTube"
    ]
  },
  {
    "domain": "jeffwylerhondaautomall.com",
    "title": "Jeff Wyler Honda Auto Mall: Honda Dealership in Louisville, KY",
    "business_name": "",
    "country": "USA",
    "seo_score": 92,
    "tech_spend": 28735,
    "crawled_at": "2025-10-31T03:34:37.603679798Z",
    "technologies": [
      "Akamai Global Host",
      "Alternate Protocol",
      "Amazon WAF Blocked",
      "Apture Linking Platform",
      "Coming Soon Page",
      "ComplyAuto",
      "Content Delivery Network",
      "DAV",
      "Dealer.com",
      "Facebook Conversion Tracking",
      "Facebook Login",
      "Facebook Messenger Platform",
      "Facebook Pixel",
      "Facebook Reseller",
      "Facebook Tag API",
      "Financial Services Guide",
      "GZIP Module",
      "GetResponse",
      "GitHub Hosting",
      "Google Analytics",
      "Google My Business",
      "Google Related Website Sites",
      "Google Tag Manager",
      "Instagram Follow Button",
      "LaunchDarkly",
      "New Relic",
      "Nginx",
      "PWA",
      "Perl",
      "QUIC",
      "Site.pro",
      "SiteW",
      "Subversion",
      "Tailwind CSS",
      "Thank You",
      "Twitter Ads",
      "UTF-8",
      "Underscores",
      "VinSolutions",
      "YouTube",
      "dc.js"
    ]
  },
  {
    "domain": "jeffwylernissanofcincinnati.com",
    "title": "Jeff Wyler Nissan of Cincinnati: Nissan Dealership in Cincinnati, OH",
    "business_name": "",
    "country": "USA",
    "seo_score": 87,
    "tech_spend": 144935,
    "crawled_at": "2025-10-31T03:34:37.577521252Z",
    "technologies": [
      "AWS WAF Challenge",
      "Adobe Marketing Cloud",
      "Akamai Global Host",
      "Alternate Protocol",
      "Amazon WAF Blocked",
      "Apture Linking Platform",
      "Better Lead Generation Services",
      "Call to Visit",
      "Coming Soon Page",
      "ComplyAuto",
      "Content Delivery Network",
      "DAV",
      "Dealer.com",
      "Facebook Conversion Tracking",
      "Facebook Login",
      "Facebook Messenger Platform",
      "Facebook Pixel",
      "Facebook Reseller",
      "Facebook Tag API",
      "Financial Services Guide",
      "GZIP Module",
      "GetResponse",
      "GitHub Hosting",
      "Google Analytics",
      "Google My Business",
      "Google Related Website Sites",
      "Google Tag Manager",
      "Instagram Follow Button",
      "LaunchDarkly",
      "New Relic",
      "Nginx",
      "PWA",
      "QUIC",
      "Site.pro",
      "SiteW",
      "Tailwind CSS",
      "Thank You",
      "Twitter Ads",
      "UTF-8",
      "Underscores",
      "University or College",
      "VinSolutions",
      "YouTube",
      "dc.js"
    ]
  },
  {
    "domain": "jeffwylerclarksvilletoyota.com",
    "title": "Jeff Wyler Toyota of Clarksville: Toyota dealership in Clarksville, IN",
    "business_name": "",
    "country": "USA",
    "seo_score": 87,
    "tech_spend": 28735,
    "crawled_at": "2025-10-31T03:21:03.591533045Z",
    "technologies": [
      "Akamai Global Host",
      "Alternate Protocol",
      "Amazon WAF Blocked",
      "Apture Linking Platform",
      "Coming Soon Page",
      "ComplyAuto",
      "Content Delivery Network",
      "DAV",
      "Dealer.com",
      "Facebook Conversion Tracking",
      "Facebook Login",
      "Facebook Messenger Platform",
      "Facebook Pixel",
      "Facebook Reseller",
      "Facebook Tag API",
      "GZIP Module",
      "GetResponse",
      "GitHub Hosting",
      "Google Analytics",
      "Google My Business",
      "Google Related Website Sites",
      "Google Tag Manager",
      "LaunchDarkly",
      "New Relic",
      "Nginx",
      "QUIC",
      "Site.pro",
      "SiteW",
      "Tailwind CSS",
      "UTF-8",
      "Underscores",
      "University or College",
      "VinSolutions",
      "dc.js",
      "shadcn ui"
    ]
  },
  {
    "domain": "wylereastgate.com",
    "title": "Jeff Wyler Eastgate Auto Mall: New Chevrolet, Chrysler, Hyundai, Jeep, Kia, Mazda, Nissan, Dodge, RAM Dealerships in Batavia, OH",
    "business_name": "",
    "country": "USA",
    "seo_score": 82,
    "tech_spend": 46375,
    "crawled_at": "2025-10-31T01:34:41.028463126Z",
    "technologies": [
      "AWS WAF Challenge",
      "Akamai Global Host",
      "Alternate Protocol",
      "Amazon WAF Blocked",
      "Apture Linking Platform",
      "Better Lead Generation Services",
      "Call to Visit",
      "Coming Soon Page",
      "ComplyAuto",
      "Content Delivery Network",
      "DAV",
      "Dealer.com",
      "Express",
      "Facebook Conversion Tracking",
      "Facebook Login",
      "Facebook Messenger Platform",
      "Facebook Pixel",
      "Facebook Reseller",
      "Facebook Tag API",
      "GZIP Module",
      "GetResponse",
      "GitHub Hosting",
      "Google Analytics",
      "Google My Business",
      "Google Related Website Sites",
      "Google Tag Manager",
      "LaunchDarkly",
      "New Relic",
      "Nginx",
      "Parcel",
      "QUIC",
      "Segment",
      "Segment Consent Manager",
      "Site.pro",
      "SiteW",
      "UTF-8",
      "Underscores",
      "VinSolutions",
      "dc.js",
      "eLand",
      "shadcn ui"
    ]
  },
  {
    "domain": "netsofoundation.org",
    "title": "NetSo Foundation NPC",
    "business_name": "",
    "country": "ZAF",
    "seo_score": 62,
    "tech_spend": 20000,
    "crawled_at": "2025-10-30T20:10:03.673341445Z",
    "technologies": [
      "Google My Business",
      "Google Play",
      "InitiativeS",
      "LiteSpeed",
      "Tailwind CSS",
      "VinSolutions",
      "shadcn ui"
    ]
  },
  {
    "domain": "elevinsolutions.com",
    "title": "Empowering Entrepreneurs - ELEVIN Solutions",
    "business_name": "ELEVIN Solutions",
    "country": "USA",
    "seo_score": 87,
    "tech_spend": 80793,
    "crawled_at": "2025-10-29T12:14:49.663219379Z",
    "technologies": [
      "AWS WAF Challenge",
      "Alternate Protocol",
      "Automattic",
      "Better Lead Generation Services",
      "Cloudflare",
      "Contact Form Plugin",
      "Content Delivery Network",
      "DAV",
      "Doctor.com",
      "EmbedPress",
      "Facebook Conversion Tracking",
      "Facebook Login",
      "Facebook Messenger Platform",
      "Facebook Pixel",
      "Facebook Reseller",
      "Facebook Tag API",
      "GoDaddy",
      "Google Analytics",
      "Google Cloud DNS",
      "Google Font API",
      "Google My Business",
      "Google Tag Manager",
      "Hotjar",
      "HubSpot Conversations",
      "HubSpot WordPress Plugin",
      "Hubspot",
      "Instagram Follow Button",
      "Jetpack",
      "Mesmerize Companion",
      "Microdata for Google Shopping",
      "PHP",
      "QUIC",
      "Tailwind CSS",
      "Theme In WP",
      "UTF-8",
      "University or College",
      "VinSolutions",
      "Wangsu",
      "WordPress",
      "WordPress Multisite",
      "WordPress Stats",
      "YouTube",
      "jQuery",
      "reCAPTCHA"
    ]
  },
  {
    "domain": "jeffwylerkingsnissan.com",
    "title": "Jeff Wyler Kings Nissan: Nissan Dealership in Cincinnati, OH",
    "business_name": "",
    "country": "USA",
    "seo_score": 87,
    "tech_spend": 144935,
    "crawled_at": "2025-10-29T02:10:54.294761179Z",
    "technologies": [
      "AWS WAF Challenge",
      "Adobe Marketing Cloud",
      "Akamai Global Host",
      "Alternate Protocol",
      "Amazon WAF Blocked",
      "Apture Linking Platform",
      "Better Lead Generation Services",
      "Call to Visit",
      "Coming Soon Page",
      "ComplyAuto",
      "Content Delivery Network",
      "DAV",
      "Dealer.com",
      "Facebook Conversion Tracking",
      "Facebook Login",
      "Facebook Messenger Platform",
      "Facebook Pixel",
      "Facebook Reseller",
      "Facebook Tag API",
      "Financial Services Guide",
      "GZIP Module",
      "GetResponse",
      "GitHub Hosting",
      "Google Analytics",
      "Google My Business",
      "Google Related Website Sites",
      "Google Tag Manager",
      "Instagram Follow Button",
      "LaunchDarkly",
      "New Relic",
      "Nginx",
      "PWA",
      "QUIC",
      "Site.pro",
      "SiteW",
      "Tailwind CSS",
      "Twitter Ads",
      "UTF-8",
      "Underscores",
      "University or College",
      "VinSolutions",
      "YouTube",
      "dc.js",
      "eLand"
    ]
  },
  {
    "domain": "jeffwylerspringfield.com",
    "title": "Jeff Wyler Springfield Auto Mall: New Chevrolet, Chrysler, Dodge, Hyundai, Jeep, Kia, RAM, Toyota Dealerships in Springfield, OH",
    "business_name": "",
    "country": "JPN",
    "seo_score": 82,
    "tech_spend": 29935,
    "crawled_at": "2025-10-28T21:32:10.337893796Z",
    "technologies": [
      "Akamai Global Host",
      "Alternate Protocol",
      "Amazon WAF Blocked",
      "Apture Linking Platform",
      "Call to Visit",
      "Coming Soon Page",
      "ComplyAuto",
      "Content Delivery Network",
      "DAV",
      "Dealer.com",
      "Express",
      "Facebook Conversion Tracking",
      "Facebook Login",
      "Facebook Messenger Platform",
      "Facebook Pixel",
      "Facebook Reseller",
      "Facebook Tag API",
      "Financial Services Guide",
      "GZIP Module",
      "GetResponse",
      "GitHub Hosting",
      "Google Analytics",
      "Google My Business",
      "Google Related Website Sites",
      "Google Tag Manager",
      "LaunchDarkly",
      "New Relic",
      "Nginx",
      "Parcel",
      "QUIC",
      "Site.pro",
      "SiteW",
      "UTF-8",
      "Underscores",
      "VinSolutions",
      "dc.js",
      "shadcn ui"
    ]
  },
  {
    "domain": "dealershipcloser.com",
    "title": "24/7 Digital Salesperson",
    "business_name": "",
    "country": "",
    "seo_score": 50,
    "tech_spend": 8000,
    "crawled_at": "2025-10-27T08:02:31.642669491Z",
    "technologies": [
      "Content Delivery Network",
      "Netlify",
      "UTF-8",
      "VinSolutions"
    ]
  }
]